gitlab_projects_issues/__init__.py
gitlab_projects_issues/__main__.py
gitlab_projects_issues/cli/__init__.py
gitlab_projects_issues/cli/entrypoint.py
gitlab_projects_issues/cli/main.py
gitlab_projects_issues/features/__init__.py
gitlab_projects_issues/features/gitlab.py
gitlab_projects_issues/package/__init__.py
gitlab_projects_issues/package/bundle.py
gitlab_projects_issues/package/settings.py
gitlab_projects_issues/package/updates.py
gitlab_projects_issues/package/version.py
gitlab_projects_issues/prints/__init__.py
gitlab_projects_issues/prints/boxes.py
gitlab_projects_issues/prints/colors.py
gitlab_projects_issues/system/__init__.py
gitlab_projects_issues/system/platform.py
gitlab_projects_issues/types/__init__.py
gitlab_projects_issues/types/environments.py
gitlab_projects_issues/types/gitlab.py
gitlab_projects_issues/types/milestones.py
gitlab_projects_issues/types/statistics.py
gitlab_projects_issues/types/strings.py
gitlab_projects_issues-4.1.0.dist-info/licenses/LICENSE
gitlab_projects_issues-4.1.0.dist-info/METADATA
gitlab_projects_issues-4.1.0.dist-info/WHEEL
gitlab_projects_issues-4.1.0.dist-info/entry_points.txt
gitlab_projects_issues-4.1.0.dist-info/top_level.txt
gitlab_projects_issues-4.1.0.dist-info/RECORD
