Metadata-Version: 2.4
Name: gitlab-projects-issues
Version: 4.1.0
Summary: Generate GitLab project issues and milestones statistics automatically
Home-page: https://gitlab.com/RadianDevCore/tools/gitlab-projects-issues
Author: Adrian DC
Author-email: radian.dc@gmail.com
License: Apache License 2.0
Project-URL: Bug Reports, https://gitlab.com/RadianDevCore/tools/gitlab-projects-issues/-/issues
Project-URL: Changelog, https://gitlab.com/RadianDevCore/tools/gitlab-projects-issues/blob/main/CHANGELOG.md
Project-URL: Documentation, https://gitlab.com/RadianDevCore/tools/gitlab-projects-issues#gitlab-projects-issues
Project-URL: Source, https://gitlab.com/RadianDevCore/tools/gitlab-projects-issues
Project-URL: Statistics, https://pypistats.org/packages/gitlab-projects-issues
Keywords: gitlab projects issues milestones
Classifier: Environment :: Console
Classifier: Intended Audience :: Developers
Classifier: License :: OSI Approved :: Apache Software License
Classifier: Operating System :: OS Independent
Classifier: Programming Language :: Python :: 3
Classifier: Programming Language :: Python :: 3.8
Classifier: Programming Language :: Python :: 3.9
Classifier: Programming Language :: Python :: 3.10
Classifier: Programming Language :: Python :: 3.11
Classifier: Programming Language :: Python :: 3.12
Classifier: Programming Language :: Python :: 3.13
Classifier: Topic :: Software Development
Classifier: Topic :: Utilities
Requires-Python: >=3,!=3.0.*,!=3.1.*,!=3.2.*,!=3.3.*,!=3.4.*,!=3.5.*,!=3.6.*,!=3.7.*
License-File: LICENSE
Requires-Dist: colored>=1.4.2
Requires-Dist: importlib-metadata>=8.5.0
Requires-Dist: packaging>=24.0
Requires-Dist: python-gitlab>=4.4.0
Requires-Dist: setuptools>=45.1.0
Requires-Dist: update_checker>=0.18.0
Dynamic: author
Dynamic: author-email
Dynamic: classifier
Dynamic: description
Dynamic: description-content-type
Dynamic: home-page
Dynamic: keywords
Dynamic: license
Dynamic: license-file
Dynamic: project-url
Dynamic: requires-dist
Dynamic: requires-python
Dynamic: summary
